setup.py
waytwo/__init__.py
waytwo.egg-info/PKG-INFO
waytwo.egg-info/SOURCES.txt
waytwo.egg-info/dependency_links.txt
waytwo.egg-info/requires.txt
waytwo.egg-info/top_level.txt