Metadata-Version: 1.1
Name: waytwo
Version: 0.0.1
Summary: Automated REST API for way2sms
Home-page: https://github.com/gowtham-sai/way2sms
Author: Gowtham Sai
Author-email: hello@gowtham-sai.com
License: Way2sms API Wrapper
Platform: any
Classifier: Programming Language :: Python
Classifier: Development Status :: 1 - Planning
Classifier: Natural Language :: English
Classifier: Environment :: MacOS X
Classifier: Intended Audience :: End Users/Desktop
Classifier: License :: OSI Approved :: GNU General Public License v2 (GPLv2)
Classifier: Operating System :: OS Independent
Classifier: Topic :: Software Development :: Libraries :: Python Modules
Classifier: Topic :: Software Development :: Libraries :: Application Frameworks
Classifier: Topic :: Internet :: WWW/HTTP :: Dynamic Content
